Metadata-Version: 2.4
Name: streamlit-position-selector-new-new
Version: 0.1.1
Summary: Streamlit component for chart position selection and management
Project-URL: Homepage, https://github.com/seu-usuario/streamlit-chart-positions
Project-URL: Repository, https://github.com/seu-usuario/streamlit-chart-positions
Project-URL: Issues, https://github.com/seu-usuario/streamlit-chart-positions/issues
Author-email: Seu Nome <seu.email@exemplo.com>
Maintainer-email: Seu Nome <seu.email@exemplo.com>
License: MIT
License-File: LICENSE
Keywords: chart,component,positions,streamlit,visualization
Classifier: Development Status :: 4 - Beta
Classifier: Intended Audience :: Developers
Classifier: License :: OSI Approved :: MIT License
Classifier: Programming Language :: Python :: 3
Classifier: Programming Language :: Python :: 3.7
Classifier: Programming Language :: Python :: 3.8
Classifier: Programming Language :: Python :: 3.9
Classifier: Programming Language :: Python :: 3.10
Classifier: Programming Language :: Python :: 3.11
Classifier: Topic :: Scientific/Engineering :: Visualization
Classifier: Topic :: Software Development :: Libraries :: Python Modules
Requires-Python: >=3.7
Requires-Dist: streamlit>=0.63
Provides-Extra: devel
Requires-Dist: playwright==1.48.0; extra == 'devel'
Requires-Dist: pytest-playwright-snapshot==1.0; extra == 'devel'
Requires-Dist: pytest-rerunfailures==12.0; extra == 'devel'
Requires-Dist: pytest==7.4.0; extra == 'devel'
Requires-Dist: requests==2.31.0; extra == 'devel'
Requires-Dist: wheel; extra == 'devel'
